CHANGES.txt
CREDITS.txt
MANIFEST.in
README.rst
bootstrap.py
buildout.cfg
setup.py
pyramid_bowerstatic/__init__.py
pyramid_bowerstatic.egg-info/PKG-INFO
pyramid_bowerstatic.egg-info/SOURCES.txt
pyramid_bowerstatic.egg-info/dependency_links.txt
pyramid_bowerstatic.egg-info/namespace_packages.txt
pyramid_bowerstatic.egg-info/not-zip-safe
pyramid_bowerstatic.egg-info/requires.txt
pyramid_bowerstatic.egg-info/top_level.txt
pyramid_bowerstatic/tests/__init__.py
pyramid_bowerstatic/tests/test_static.py