Metadata-Version: 1.0
Name: pyramid-bowerstatic
Version: 0.2
Summary: BowerStatic integration for Pyramid
Home-page: http://pypi.python.org/pypi/pyramid_bowerstatic
Author: Marc Rijken
Author-email: marc@rijken.org
License: BSD
Keywords: pyramid bowerstatic bower
Platform: UNKNOWN
